endpoints/__init__.py
endpoints/log_utils.py
endpoints/model.py
endpoints/schema.py
endpoints/settings.py
endpoints/utils.py
endpoints/cli/__init__.py
endpoints/cli/cli.py
endpoints/cli/options.py
endpoints/cli/utils.py
endpoints/cli/sagemaker/__init__.py
endpoints/cli/sagemaker/commands.py
endpoints/cli/snowflake/__init_.py
endpoints/cli/snowflake/commands.py
endpoints/container/__init__.py
endpoints/container/base_inference_model.py
endpoints/container/serve.py
endpoints/container/utils.py
endpoints/container/routers/healthcheck.py
endpoints/container/routers/sagemaker.py
endpoints/container/routers/snowflake.py
endpoints/container/templates/__init__.py
endpoints/container/templates/app.py
endpoints/container/templates/custom_logging.py
endpoints/container/templates/endpoint_logic.py
endpoints/container/templates/installer.py
endpoints/container/templates/model_loader.py
endpoints/container/templates/routers/__init__.py
endpoints/container/templates/routers/sagemaker.py
endpoints/container/templates/routers/snowflake.py
endpoints/databricks/__init__.py
endpoints/databricks/catalog.py
endpoints/databricks/generate_job_payload.py
endpoints/databricks/generate_nb.py
endpoints/databricks/listing.py
endpoints/databricks/share.py
endpoints/databricks/ci_cd/create_databricks_uc_cluster.py
endpoints/databricks/ci_cd/installer.py
endpoints/databricks/ci_cd/submit_publish_job.py
endpoints/env/bin/find_spark_home.py
endpoints/env/bin/jp.py
endpoints/johnsnowlabs/__init__.py
endpoints/johnsnowlabs/encoder.py
endpoints/johnsnowlabs/inference_model.py
endpoints/johnsnowlabs/model_loader.py
endpoints/johnsnowlabs/utils.py
endpoints/sagemaker/__init__.py
endpoints/sagemaker/ci_cd/__init__.py
endpoints/sagemaker/ci_cd/run_sagemaker_pipeline.py
endpoints/snowflake/__init__.py
endpoints/snowflake/producer.py
endpoints/snowflake/snowflake_operations.py
endpoints/snowflake/templates/streamlit_app.py
ksh_jsl_inference-0.1.0.dist-info/LICENSE
ksh_jsl_inference-0.1.0.dist-info/METADATA
ksh_jsl_inference-0.1.0.dist-info/WHEEL
ksh_jsl_inference-0.1.0.dist-info/entry_points.txt
ksh_jsl_inference-0.1.0.dist-info/top_level.txt
ksh_jsl_inference-0.1.0.dist-info/RECORD
