Metadata-Version: 2.1
Name: ksh_jsl_inference
Version: 0.1.0
Maintainer-email: Kshitiz Shakya <kshitiz@johnsnowlabs.com>
License: Copyright 2015-2024 © John Snow Labs Inc.
Requires-Python: >=3.6
License-File: LICENSE
Requires-Dist: click <9,>=7.0
Requires-Dist: johnsnowlabs >=5.4.0
Requires-Dist: fastapi
Requires-Dist: uvicorn
